[
    {
        "เลขทะเบียน": "0735538002164",
        "ประกอบธุรกิจ": "ประกอบกิจการโรงโม่และย่อยหิน",
        "หมวดธุรกิจ": "การทำเหมืองหินที่ใช้ในการก่อสร้าง",
        "สถานะ": "ยังดำเนินกิจการอยู่",
        "วันที่จดทะเบียน": "19 ตุลาคม 2538",
        "ทุนจดทะเบียน": "30,000,000 บาท",
        "ที่ตั้ง": "565 หมู่ที่ 5 ตำบลจรเข้สามพัน อำเภออู่ทอง จ.สุพรรณบุรี",
        "ชื่อบริษัทภาษาอังกฤษ": "KANCHANA SILAPAN COMPANY LIMITED",
        "ชื่อบริษัทภาษาไทย": "บริษัท กาญจนาศิลาภัณฑ์ จำกัด",
        "ข้อมูลสำหรับการติดต่อ": false,
        "ที่มา": "https://www.dataforthai.com/company/0735538002164/"
    },
    {
        "เลขทะเบียน": "0345540000231",
        "ประกอบธุรกิจ": "",
        "สถานะ": "ยังดำเนินกิจการอยู่",
        "วันที่จดทะเบียน": "16 กรกฎาคม 2540",
        "ทุนจดทะเบียน": "100,000,000 บาท",
        "ที่ตั้ง": "399 หมู่บ้านเกษตรพัฒนา หมู่ที่ 15 ตำบลบุเปือย อำเภอน้ำยืน จ.อุบลราชธานี 34260",
        "หมวดธุรกิจ": "การทำเหมืองหินที่ใช้ในการก่อสร้าง",
        "ชื่อบริษัทภาษาอังกฤษ": "KITTIWADEE SILAPHANICH CO., LTD.",
        "ชื่อบริษัทภาษาไทย": "บริษัท กิตติวดีศิลาพาณิชย์ จำกัด",
        "ข้อมูลสำหรับการติดต่อ": false,
        "ที่มา": "https://www.dataforthai.com/company/0345540000231/"
    },
    {
        "เลขทะเบียน": "0125542000826",
        "ประกอบธุรกิจ": "ให้บริการบรรจุ,ตัดแต่ง,ประกอบกระเบื้องเซรามิค,หินจริง,หินเทียมให้เช่าอาคาร",
        "หมวดธุรกิจ": "การทำเหมืองหินที่ใช้ในการก่อสร้าง",
        "สถานะ": "ยังดำเนินกิจการอยู่",
        "วันที่จดทะเบียน": "8 กุมภาพันธ์ 2542",
        "ทุนจดทะเบียน": "50,000,000 บาท",
        "ที่ตั้ง": "82/90 หมู่ที่ 6 ถนนงามวงศ์วาน แขวงทุ่งสองห้อง เขตหลักสี่ กรุงเทพมหานคร 10210",
        "ชื่อบริษัทภาษาอังกฤษ": "GRAND HOMEMART (BANG BUATHONG) CO., LTD.",
        "ชื่อบริษัทภาษาไทย": "บริษัท แกรนด์ โฮมมาร์ท กรุ๊ป จำกัด",
        "ข้อมูลสำหรับการติดต่อ": false,
        "ที่มา": "https://www.dataforthai.com/company/0125542000826/"
    },
    {
        "เลขทะเบียน": "0603546001111",
        "ประกอบธุรกิจ": "ผลิตและจำหน่ายหิน",
        "หมวดธุรกิจ": "การทำเหมืองหินที่ใช้ในการก่อสร้าง",
        "สถานะ": "แปรสภาพ เป็น บริษัท เขตศิลา จำกัด",
        "วันที่จดทะเบียน": "5 พฤศจิกายน 2546",
        "ทุนจดทะเบียน": "40,000,000 บาท",
        "ที่ตั้ง": "30 ถนนมหิดล ตำบลสุเทพ อำเภอเมืองเชียงใหม่ จ.เชียงใหม่ 50200",
        "ชื่อบริษัทภาษาอังกฤษ": "KET SIRA LIMITED PARTNERSHIP",
        "ชื่อบริษัทภาษาไทย": "ห้างหุ้นส่วนจำกัด เขตศิลา",
        "ข้อมูลสำหรับการติดต่อ": false,
        "ที่มา": "https://www.dataforthai.com/company/0603546001111/"
    },
    {
        "เลขทะเบียน": "0825540000032",
        "ประกอบธุรกิจ": "การทำเหมืองหิน",
        "หมวดธุรกิจ": "การทำเหมืองหินที่ใช้ในการก่อสร้าง",
        "สถานะ": "ยังดำเนินกิจการอยู่",
        "วันที่จดทะเบียน": "20 สิงหาคม 2540",
        "ทุนจดทะเบียน": "45,000,000 บาท",
        "ข้อมูลสำหรับติดต่อ": "สมาชิก dataforthai.com สามารถดูข้อมูลการติดต่อเพิ่มเติมได้  สมัครสมาชิกฟรี",
        "ที่ตั้ง": "8/2 หมู่ที่ 1 ตำบลบางเตย อำเภอเมืองพังงา จ.พังงา 82000",
        "ชื่อบริษัทภาษาอังกฤษ": "KHAO BOR CONSTRUCTION CO., LTD.",
        "ชื่อบริษัทภาษาไทย": "บริษัท เขาบ่อ คอนสทรัคชั่น จำกัด",
        "ข้อมูลสำหรับการติดต่อ": true,
        "ที่มา": "https://www.dataforthai.com/company/0825540000032/"
    },
    {
        "เลขทะเบียน": "0545537000208",
        "ประกอบธุรกิจ": "",
        "สถานะ": "ยังดำเนินกิจการอยู่",
        "วันที่จดทะเบียน": "29 สิงหาคม 2537",
        "ทุนจดทะเบียน": "42,000,000 บาท",
        "ข้อมูลสำหรับติดต่อ": "สมาชิก dataforthai.com สามารถดูข้อมูลการติดต่อเพิ่มเติมได้  สมัครสมาชิกฟรี",
        "ที่ตั้ง": "22/12 ถนนเหมืองหิต ตำบลในเวียง อำเภอเมืองแพร่ จ.แพร่ 54000",
        "หมวดธุรกิจ": "การทำเหมืองหินที่ใช้ในการก่อสร้าง",
        "ชื่อบริษัทภาษาอังกฤษ": "KACHATARN CONSTRUCTION CO., LTD.",
        "ชื่อบริษัทภาษาไทย": "บริษัท คชาธารก่อสร้าง จำกัด",
        "ข้อมูลสำหรับการติดต่อ": true,
        "ที่มา": "https://www.dataforthai.com/company/0545537000208/"
    },
    {
        "เลขทะเบียน": "0245535000769",
        "ประกอบธุรกิจ": "โรงงานแปรรูป หินแกรนิต หินอ่อน หินทราย และหินประดับ",
        "หมวดธุรกิจ": "การผลิตผลิตภัณฑ์หินที่ใช้ในการก่อสร้าง",
        "สถานะ": "ยังดำเนินกิจการอยู่",
        "วันที่จดทะเบียน": "24 กันยายน 2535",
        "ทุนจดทะเบียน": "30,000,000 บาท",
        "ที่ตั้ง": "178 หมู่ 5 ตำบลโคกไทย อำเภอศรีมโหสถ จ.ปราจีนบุรี 25190",
        "ชื่อบริษัทภาษาอังกฤษ": "GRANITE SAW CO., LTD.",
        "ชื่อบริษัทภาษาไทย": "บริษัท คีรี อินดัสทรี จำกัด",
        "ข้อมูลสำหรับการติดต่อ": false,
        "ที่มา": "https://www.dataforthai.com/company/0245535000769/"
    },
    {
        "เลขทะเบียน": "0815542000081",
        "ประกอบธุรกิจ": "โรงโม่หิน",
        "หมวดธุรกิจ": "การทำเหมืองหินที่ใช้ในการก่อสร้าง",
        "สถานะ": "ยังดำเนินกิจการอยู่",
        "วันที่จดทะเบียน": "19 เมษายน 2542",
        "ทุนจดทะเบียน": "70,000,000 บาท",
        "ที่ตั้ง": "58 หมู่ที่ 5 ตำบลเขาพนม อำเภอเขาพนม จ.กระบี่ 81140",
        "ชื่อบริษัทภาษาอังกฤษ": "",
        "ชื่อบริษัทภาษาไทย": "บริษัท เคียงตะวัน โม่หิน จำกัด",
        "ข้อมูลสำหรับการติดต่อ": false,
        "ที่มา": "https://www.dataforthai.com/company/0815542000081/"
    },
    {
        "เลขทะเบียน": "0953528000157",
        "ประกอบธุรกิจ": "ผลิตและจำหน่ายหินย่อย",
        "หมวดธุรกิจ": "การทำเหมืองหินที่ใช้ในการก่อสร้าง",
        "สถานะ": "ยังดำเนินกิจการอยู่",
        "วันที่จดทะเบียน": "11 มิถุนายน 2528",
        "ทุนจดทะเบียน": "60,000,000 บาท",
        "ข้อมูลสำหรับติดต่อ": "สมาชิก dataforthai.com สามารถดูข้อมูลการติดต่อเพิ่มเติมได้  สมัครสมาชิกฟรี",
        "ที่ตั้ง": "79/3 หมู่ที่ 1 ตำบลลิดล อำเภอเมืองยะลา จ.ยะลา 95160",
        "ชื่อบริษัทภาษาอังกฤษ": "CHAREONTHIP CIVIL LTD., PART.",
        "ชื่อบริษัทภาษาไทย": "ห้างหุ้นส่วนจำกัด เจริญทิพย์การโยธา",
        "ข้อมูลสำหรับการติดต่อ": true,
        "ที่มา": "https://www.dataforthai.com/company/0953528000157/"
    },
    {
        "เลขทะเบียน": "0923510000139",
        "ประกอบธุรกิจ": "ประกอบกิจการทำเหมืองหินที่ไม่ใช้ในการก่อสร้าง",
        "หมวดธุรกิจ": "การทำเหมืองหินที่ใช้ในการก่อสร้าง",
        "สถานะ": "ยังดำเนินกิจการอยู่",
        "วันที่จดทะเบียน": "27 มิถุนายน 2510",
        "ทุนจดทะเบียน": "130,000,000 บาท",
        "ที่ตั้ง": "หมู่ที่ 3 ถนนเพชรเกษม ตำบลปากคม อำเภอห้วยยอด จ.ตรัง 92130",
        "ชื่อบริษัทภาษาอังกฤษ": "NON'",
        "ชื่อบริษัทภาษาไทย": "ห้างหุ้นส่วนจำกัด โจมทองศิลา",
        "ข้อมูลสำหรับการติดต่อ": false,
        "ที่มา": "https://www.dataforthai.com/company/0923510000139/"
    },
    {
        "เลขทะเบียน": "0415543000461",
        "ประกอบธุรกิจ": "ประกอบกิจการ ระเบิดหิน โรงโม่หินและย่อยหิน",
        "หมวดธุรกิจ": "การทำเหมืองหินที่ใช้ในการก่อสร้าง",
        "สถานะ": "ยังดำเนินกิจการอยู่",
        "วันที่จดทะเบียน": "1 ธันวาคม 2543",
        "ทุนจดทะเบียน": "50,000,000 บาท",
        "ที่ตั้ง": "345/32 หมู่ที่ 2 ซอยบ้านโพธิ์สว่าง ตำบลหมากแข้ง อำเภอเมืองอุดรธานี จ.อุดรธานี 41000",
        "ชื่อบริษัทภาษาอังกฤษ": "",
        "ชื่อบริษัทภาษาไทย": "บริษัท ช.นิยม จำกัด",
        "ข้อมูลสำหรับการติดต่อ": false,
        "ที่มา": "https://www.dataforthai.com/company/0415543000461/"
    },
    {
        "เลขทะเบียน": "0105562022876",
        "ประกอบธุรกิจ": "เหมืองแร่ ระเบิดหิน ย่อยหิน ทำการขอสัมปทานภูเขา",
        "หมวดธุรกิจ": "การทำเหมืองหินที่ใช้ในการก่อสร้าง",
        "สถานะ": "ยังดำเนินกิจการอยู่",
        "วันที่จดทะเบียน": "4 กุมภาพันธ์ 2562",
        "ทุนจดทะเบียน": "150,000,000 บาท",
        "ข้อมูลสำหรับติดต่อ": "สมาชิก dataforthai.com สามารถดูข้อมูลการติดต่อเพิ่มเติมได้  สมัครสมาชิกฟรี",
        "ที่ตั้ง": "86/9 หมู่ที่ 9 ตำบลบางแก้ว อำเภอบางพลี จ.สมุทรปราการ 10540",
        "ชื่อบริษัทภาษาอังกฤษ": "CHONBURI HINSUAY COMPANY LIMITED",
        "ชื่อบริษัทภาษาไทย": "บริษัท ชลบุรี หินสวย จำกัด",
        "ข้อมูลสำหรับการติดต่อ": true,
        "ที่มา": "https://www.dataforthai.com/company/0105562022876/"
    },
    {
        "เลขทะเบียน": "0505556000048",
        "ประกอบธุรกิจ": "",
        "สถานะ": "ยังดำเนินกิจการอยู่",
        "วันที่จดทะเบียน": "3 มกราคม 2556",
        "ทุนจดทะเบียน": "60,000,000 บาท",
        "ที่ตั้ง": "99 หมู่ที่ 21 ตำบลสบเตี๊ยะ อำเภอจอมทอง จ.เชียงใหม่ 50160",
        "หมวดธุรกิจ": "การทำเหมืองหินที่ใช้ในการก่อสร้าง",
        "ชื่อบริษัทภาษาอังกฤษ": "CHIANGMAI T.D. COMPANY LIMITED",
        "ชื่อบริษัทภาษาไทย": "บริษัท เชียงใหม่ ที.ดี. จำกัด",
        "ข้อมูลสำหรับการติดต่อ": false,
        "ที่มา": "https://www.dataforthai.com/company/0505556000048/"
    },
    {
        "เลขทะเบียน": "0503536004101",
        "ประกอบธุรกิจ": "การทำเหมืองหิน",
        "หมวดธุรกิจ": "การทำเหมืองหินที่ใช้ในการก่อสร้าง",
        "สถานะ": "แปรสภาพ เป็น บริษัท เชียงใหม่ ที.ดี. จำกัด",
        "วันที่จดทะเบียน": "30 กันยายน 2536",
        "ทุนจดทะเบียน": "60,000,000 บาท",
        "ที่ตั้ง": "211/1 หมู่ที่ 6 ตำบลสบเตี๊ยะ อำเภอจอมทอง จ.เชียงใหม่ 50160",
        "ชื่อบริษัทภาษาอังกฤษ": "CHIANGMAI T.D. LIMITED PARTNERSHIP",
        "ชื่อบริษัทภาษาไทย": "ห้างหุ้นส่วนจำกัด เชียงใหม่ ที.ดี.",
        "ข้อมูลสำหรับการติดต่อ": false,
        "ที่มา": "https://www.dataforthai.com/company/0503536004101/"
    },
    {
        "เลขทะเบียน": "0415528000048",
        "ประกอบธุรกิจ": "",
        "สถานะ": "ยังดำเนินกิจการอยู่",
        "วันที่จดทะเบียน": "29 เมษายน 2528",
        "ทุนจดทะเบียน": "30,000,000 บาท",
        "ที่ตั้ง": "88/88 หมู่ที่ 7 ซอยบ้านโนนยาง ตำบลหมากแข้ง อำเภอเมืองอุดรธานี จ.อุดรธานี 41000",
        "หมวดธุรกิจ": "การทำเหมืองหินที่ใช้ในการก่อสร้าง",
        "ชื่อบริษัทภาษาอังกฤษ": "",
        "ชื่อบริษัทภาษาไทย": "บริษัท โชคอนันต์ก่อสร้างอุดรธานี จำกัด",
        "ข้อมูลสำหรับการติดต่อ": false,
        "ที่มา": "https://www.dataforthai.com/company/0415528000048/"
    },
    {
        "เลขทะเบียน": "0105538024937",
        "ประกอบธุรกิจ": "การทำเหมืองแร่และเหมืองหิน",
        "หมวดธุรกิจ": "การทำเหมืองหินที่ใช้ในการก่อสร้าง",
        "สถานะ": "ยังดำเนินกิจการอยู่",
        "วันที่จดทะเบียน": "24 กุมภาพันธ์ 2538",
        "ทุนจดทะเบียน": "250,000,000 บาท",
        "ที่ตั้ง": "1000/7-8 อาคารลิเบอร์ตี้ พลาซ่า ชั้นที่ 19 ซอยสุขุมวิท 55 (ทองหล่อ) แขวงคลองตันเหนือ เขตวัฒนา กรุงเทพมหานคร 10110",
        "ชื่อบริษัทภาษาอังกฤษ": "SOUTHEAST ASIA POWER CONSULTANTS COMPANY LIMITED",
        "ชื่อบริษัทภาษาไทย": "บริษัท เซ้าอีสท์เอเซีย เพาเวอร์ คอนซัลแตนท์ จำกัด",
        "ข้อมูลสำหรับการติดต่อ": false,
        "ที่มา": "https://www.dataforthai.com/company/0105538024937/"
    },
    {
        "เลขทะเบียน": "0805540000270",
        "ประกอบธุรกิจ": "ประกอบกิจการเหมืองหิน",
        "หมวดธุรกิจ": "การทำเหมืองหินที่ใช้ในการก่อสร้าง",
        "สถานะ": "ยังดำเนินกิจการอยู่",
        "วันที่จดทะเบียน": "29 เมษายน 2540",
        "ทุนจดทะเบียน": "148,000,000 บาท",
        "สมัครงาน / ดูตำแหน่งงานว่าง": "ดูตำแหน่งงานจาก JOBTHAI",
        "ที่ตั้ง": "599 หมู่ที่ 5 ตำบลปากพูน อำเภอเมืองนครศรีธรรมราช จ.นครศรีธรรมราช 80000",
        "ชื่อบริษัทภาษาอังกฤษ": "",
        "ชื่อบริษัทภาษาไทย": "บริษัท ทรัพย์ดี จำกัด",
        "ข้อมูลสำหรับการติดต่อ": false,
        "ที่มา": "https://www.dataforthai.com/company/0805540000270/"
    },
    {
        "เลขทะเบียน": "0425552000044",
        "ประกอบธุรกิจ": "ธุรกิจโรงโม่หินและย่อยหิน",
        "หมวดธุรกิจ": "การทำเหมืองหินที่ใช้ในการก่อสร้าง",
        "สถานะ": "ยังดำเนินกิจการอยู่",
        "วันที่จดทะเบียน": "12 กุมภาพันธ์ 2552",
        "ทุนจดทะเบียน": "22,500,000 บาท",
        "ที่ตั้ง": "128 หมู่ที่ 7 ตำบลทรัพย์ไพวัลย์ อำเภอเอราวัณ จ.เลย 42220",
        "ชื่อบริษัทภาษาอังกฤษ": "SUBPAIWAN KANSILA COMPANY LIMITED",
        "ชื่อบริษัทภาษาไทย": "บริษัท ทรัพย์ไพวัลย์ การศิลา จำกัด",
        "ข้อมูลสำหรับการติดต่อ": false,
        "ที่มา": "https://www.dataforthai.com/company/0425552000044/"
    },
    {
        "เลขทะเบียน": "0203521000662",
        "ประกอบธุรกิจ": "ผลิต ค้าปลีกและจำหน่ายหิน",
        "หมวดธุรกิจ": "การทำเหมืองหินที่ใช้ในการก่อสร้าง",
        "สถานะ": "แปรสภาพ เป็น บริษัท ทัศนาชลบุรี จำกัด",
        "วันที่จดทะเบียน": "14 กันยายน 2521",
        "ทุนจดทะเบียน": "300,000,000 บาท",
        "สมัครงาน / ดูตำแหน่งงานว่าง": "ดูตำแหน่งงานจาก JOBTHAI",
        "ที่ตั้ง": "9/12 หมู่ที่ 1 ตำบลห้วยกะปิ อำเภอเมืองชลบุรี จ.ชลบุรี",
        "ชื่อบริษัทภาษาอังกฤษ": "",
        "ชื่อบริษัทภาษาไทย": "ห้างหุ้นส่วนจำกัด ทัศนาชลบุรี",
        "ข้อมูลสำหรับการติดต่อ": false,
        "ที่มา": "https://www.dataforthai.com/company/0203521000662/"
    },
    {
        "เลขทะเบียน": "0105533133649",
        "ประกอบธุรกิจ": "การทำเหมืองแร่และเหมืองหิน",
        "หมวดธุรกิจ": "การทำเหมืองหินที่ใช้ในการก่อสร้าง",
        "สถานะ": "ยังดำเนินกิจการอยู่",
        "วันที่จดทะเบียน": "9 พฤศจิกายน 2533",
        "ทุนจดทะเบียน": "52,525,000 บาท",
        "ที่ตั้ง": "1000/7-8 อาคารลิเบอร์ตี้ พลาซ่า ชั้น 19 ซอยสุขุมวิท 55 (ทองหล่อ) แขวงคลองตันเหนือ เขตวัฒนา กรุงเทพมหานคร 10110",
        "ชื่อบริษัทภาษาอังกฤษ": "THAI LAOS LIGNITE CO.,LTD.",
        "ชื่อบริษัทภาษาไทย": "บริษัท ไทยลาวลิกไนท์ จำกัด",
        "ข้อมูลสำหรับการติดต่อ": false,
        "ที่มา": "https://www.dataforthai.com/company/0105533133649/"
    },
    {
        "เลขทะเบียน": "0205553020091",
        "ประกอบธุรกิจ": "โรงโม่หินและขนส่งสินค้าทุกชนิด",
        "หมวดธุรกิจ": "การทำเหมืองหินที่ใช้ในการก่อสร้าง",
        "สถานะ": "ยังดำเนินกิจการอยู่",
        "วันที่จดทะเบียน": "21 กันยายน 2553",
        "ทุนจดทะเบียน": "30,000,000 บาท",
        "ที่ตั้ง": "2/4 หมู่ที่ 7 ตำบลหนองข้างคอก อำเภอเมืองชลบุรี จ.ชลบุรี 20000",
        "ชื่อบริษัทภาษาอังกฤษ": "TARNRAK CO.,LTD.",
        "ชื่อบริษัทภาษาไทย": "บริษัท ธารรัก จำกัด",
        "ข้อมูลสำหรับการติดต่อ": false,
        "ที่มา": "https://www.dataforthai.com/company/0205553020091/"
    },
    {
        "เลขทะเบียน": "0103524018865",
        "ประกอบธุรกิจ": "โรงโม่หิน",
        "หมวดธุรกิจ": "การทำเหมืองหินที่ใช้ในการก่อสร้าง",
        "สถานะ": "แปรสภาพ เป็น บริษัท ธารรัก จำกัด",
        "วันที่จดทะเบียน": "6 ตุลาคม 2524",
        "ทุนจดทะเบียน": "40,000,000 บาท",
        "ที่ตั้ง": "2/4 หมู่ที่ 7 ตำบลหนองข้างคอก อำเภอเมืองชลบุรี จ.ชลบุรี 20000",
        "ชื่อบริษัทภาษาอังกฤษ": "",
        "ชื่อบริษัทภาษาไทย": "ห้างหุ้นส่วนจำกัด ธารรัก",
        "ข้อมูลสำหรับการติดต่อ": false,
        "ที่มา": "https://www.dataforthai.com/company/0103524018865/"
    },
    {
        "เลขทะเบียน": "0805558001219",
        "ประกอบธุรกิจ": "การทำเหมืองหิน",
        "หมวดธุรกิจ": "การทำเหมืองหินที่ใช้ในการก่อสร้าง",
        "สถานะ": "ยังดำเนินกิจการอยู่",
        "วันที่จดทะเบียน": "7 สิงหาคม 2558",
        "ทุนจดทะเบียน": "50,100,000 บาท",
        "ข้อมูลสำหรับติดต่อ": "สมาชิก dataforthai.com สามารถดูข้อมูลการติดต่อเพิ่มเติมได้  สมัครสมาชิกฟรี",
        "ที่ตั้ง": "82/4 หมู่ที่ 1 ถนนกะโรม ตำบลโพธิ์เสด็จ อำเภอเมืองนครศรีธรรมราช จ.นครศรีธรรมราช 80000",
        "ชื่อบริษัทภาษาอังกฤษ": "NAKHON RATANASILA CO.,LTD.",
        "ชื่อบริษัทภาษาไทย": "บริษัท นครรัตนศิลา จำกัด",
        "ข้อมูลสำหรับการติดต่อ": true,
        "ที่มา": "https://www.dataforthai.com/company/0805558001219/"
    }
]